{
  "buildCommand" : {
    "command" : "build",
    "skipDependencies" : false,
    "style" : "buildAndRun"
  },
  "configuredTargets" : [
    {
      "guid" : "5d8615c9df03c1b927fb505ced44223156b076e820abbdc349ed78b5aecf9f29"
    }
  ],
  "containerPath" : "/Users/jaelruvalcaba/Desktop/GraphQLwithApolloSWAPI/GraphQLwithApolloSWAPI.xcodeproj",
  "continueBuildingAfterErrors" : false,
  "dependencyScope" : "workspace",
  "enableIndexBuildArena" : false,
  "hideShellScriptEnvironment" : false,
  "parameters" : {
    "action" : "build",
    "overrides" : {
      "commandLine" : {
        "table" : {

        }
      },
      "synthesized" : {
        "table" : {
          "ACTION" : "build",
          "COLOR_DIAGNOSTICS" : "YES",
          "diagnostic_message_length" : "213",
          "ENABLE_PREVIEWS" : "NO",
          "ENABLE_XOJIT_PREVIEWS" : "NO"
        }
      }
    }
  },
  "showNonLoggedProgress" : true,
  "useDryRun" : false,
  "useImplicitDependencies" : false,
  "useLegacyBuildLocations" : false,
  "useParallelTargets" : true
}